tracereq/__init__.py
tracereq/lda.py
tracereq/lsa.py
tracereq/preprocessing_evaluation.py
tracereq/vsm.py
tracereq-0.0.5.dist-info/LICENSE
tracereq-0.0.5.dist-info/METADATA
tracereq-0.0.5.dist-info/WHEEL
tracereq-0.0.5.dist-info/top_level.txt
tracereq-0.0.5.dist-info/RECORD
